{
    "name": "albâtresépia",
    "brand": "Première Peau",
    "release_year": "2025",
    "description": "A new perfume byPremière Peaufor women and men, released in2025. The scent is woody-spicy.Compare",
    "image_url": "https://media.parfumo.com/perfumes/6e/6e94c6_albatresepia-premiere-peau_1200.jpg?width=720&aspect_ratio=1:1",
    "main_accords": [
        "Woody",
        "Spicy",
        "Sweet",
        "Gourmand",
        "Smoky"
    ],
    "top_notes": [],
    "heart_notes": [],
    "base_notes": [],
    "ratings": {
        "scent": {
            "score": "7.6",
            "votes": "18 Ratings"
        },
        "durability": {
            "score": "7.8",
            "votes": "17 Ratings"
        },
        "sillage": {
            "score": "7.0",
            "votes": "18 Ratings"
        },
        "bottle": {
            "score": "9.1",
            "votes": "20 Ratings"
        }
    },
    "community_charts": {
        "Type": [
            {
                "name": "Spicy",
                "votes": 7
            },
            {
                "name": "Sweet",
                "votes": 7
            },
            {
                "name": "Smoky",
                "votes": 5
            },
            {
                "name": "Woody",
                "votes": 7
            },
            {
                "name": "Gourmand",
                "votes": 5
            },
            {
                "name": "Fougère",
                "votes": 2
            },
            {
                "name": "Earthy",
                "votes": 3
            },
            {
                "name": "Creamy",
                "votes": 4
            }
        ],
        "Style": [
            {
                "name": "Masculine",
                "votes": 8
            },
            {
                "name": "Feminine",
                "votes": 8
            },
            {
                "name": "Modern",
                "votes": 6
            }
        ],
        "Season": [
            {
                "name": "Winter",
                "votes": 8
            },
            {
                "name": "Fall",
                "votes": 8
            },
            {
                "name": "Spring",
                "votes": 2
            }
        ],
        "Occasion": [
            {
                "name": "Daily",
                "votes": 3
            },
            {
                "name": "Leisure",
                "votes": 8
            },
            {
                "name": "Night Out",
                "votes": 9
            },
            {
                "name": "Business",
                "votes": 3
            },
            {
                "name": "Evening",
                "votes": 9
            }
        ]
    }
}