{
    "name": "Bint Hind",
    "brand": "Maison Anthony Marmin",
    "release_year": "2025",
    "description": "A new perfume byMaison Anthony Marminfor women and men, released in2025.Compare",
    "image_url": "https://media.parfumo.com/perfumes/2d/2d1818_bint-hind-maison-anthony-marmin-abdul-karim-al-faransi_1200.jpg?width=720&aspect_ratio=1:1",
    "main_accords": [],
    "top_notes": [
        "Tangerine",
        "Vanilla"
    ],
    "heart_notes": [
        "May rose",
        "Sandalwood"
    ],
    "base_notes": [
        "Amber",
        "Spices"
    ],
    "ratings": {
        "bottle": {
            "score": "7.0",
            "votes": "2 Ratings"
        }
    },
    "community_charts": {}
}