{
    "name": "Black Signature",
    "brand": "Mustang Jeans",
    "release_year": "2025",
    "description": "A new perfume byMustang Jeansfor men, released in2025. It is being marketed byLuxess.Compare",
    "image_url": "https://media.parfumo.com/perfumes/78/78f4d7_black-signature-mustang-jeans_1200.jpg?width=720&aspect_ratio=1:1",
    "main_accords": [],
    "top_notes": [
        "Black pepper",
        "Cardamom",
        "Fir balsam"
    ],
    "heart_notes": [
        "Frankincense",
        "Marine notes",
        "Moss"
    ],
    "base_notes": [
        "Amber",
        "Patchouli",
        "Sandalwood",
        "Tonka bean",
        "Whisky"
    ],
    "ratings": {},
    "community_charts": {}
}