{
    "name": "Burial Bloom",
    "brand": "Graveyard Wanders",
    "release_year": "2025",
    "description": "A new perfume byGraveyard Wandersfor women and men, released in2025.Compare",
    "image_url": "https://media.parfumo.com/perfumes/f0/f03f8f_burial-bloom-perfume-mist-graveyard-wanders_1200.jpg?width=720&aspect_ratio=1:1",
    "main_accords": [],
    "top_notes": [
        "Clover",
        "Lemon zest"
    ],
    "heart_notes": [
        "Green leaves",
        "Hydrangea",
        "White lily"
    ],
    "base_notes": [
        "Musk",
        "Powder"
    ],
    "ratings": {},
    "community_charts": {}
}