{
    "name": "Dark Wild",
    "brand": "Piené",
    "release_year": "2025",
    "description": "A new perfume byPienéfor women and men, released in2025.Compare",
    "image_url": "https://media.parfumo.com/perfumes/57/57adc1_dark-wild-piene_1200.jpg?width=480&aspect_ratio=1:1",
    "main_accords": [],
    "top_notes": [
        "Bergamot",
        "Cardamom",
        "Ginger",
        "Lemon",
        "Pink pepper"
    ],
    "heart_notes": [
        "Jasmine",
        "Nutmeg",
        "Rose",
        "Ylang-ylang"
    ],
    "base_notes": [
        "Amber",
        "Labdanum",
        "Patchouli",
        "Sandalwood",
        "Vanilla"
    ],
    "ratings": {},
    "community_charts": {}
}