{
    "name": "Dusky Break",
    "brand": "Nethum",
    "release_year": "2025",
    "description": "A new perfume byNethumfor women and men, released in2025.PronunciationCompare",
    "image_url": "https://media.parfumo.com/perfumes/90/903a83_dusky-break-nethum_1200.jpg?width=720&aspect_ratio=1:1",
    "main_accords": [],
    "top_notes": [
        "Cannabis",
        "Gardenia",
        "Grapefruit",
        "Green mandarin orange",
        "Orange"
    ],
    "heart_notes": [
        "Coffee",
        "Eucalyptus",
        "Hazelnut",
        "Mint",
        "Nutmeg",
        "Pink pepper",
        "Praliné",
        "Spices"
    ],
    "base_notes": [
        "Caramelized nuts",
        "Cedarwood",
        "Chestnut",
        "Cistus",
        "Cocoa",
        "Coffee",
        "Copaiba balsam",
        "Gaiac wood",
        "Oud",
        "Patchouli",
        "Tonka bean"
    ],
    "ratings": {},
    "community_charts": {}
}