{
    "name": "Eau Qi",
    "brand": "Qiriness",
    "release_year": "2025",
    "description": "A new perfume byQirinessfor women and men, released in2025. It is being marketed byLAP Groupe.Compare",
    "image_url": "https://media.parfumo.com/perfumes/4c/4c7ea4_eau-qi-qiriness_1200.jpg?width=720&aspect_ratio=1:1",
    "main_accords": [],
    "top_notes": [
        "Basil",
        "Earl Grey tea",
        "Italian lemon zest"
    ],
    "heart_notes": [
        "Fennel",
        "Hedione",
        "Peony"
    ],
    "base_notes": [
        "Blond woods",
        "Mineral moss",
        "Musk"
    ],
    "ratings": {},
    "community_charts": {}
}