{
    "name": "Gourmand Coffee",
    "brand": "Zara",
    "release_year": "2025",
    "description": "A new perfume byZarafor women, released in2025. The scent is gourmand-sweet.Compare",
    "image_url": "https://media.parfumo.com/perfumes/79/79ecb4_gourmand-coffee-zara_1200.jpg?width=720&aspect_ratio=1:1",
    "main_accords": [
        "Gourmand",
        "Sweet",
        "Creamy",
        "Woody",
        "Spicy"
    ],
    "top_notes": [],
    "heart_notes": [],
    "base_notes": [],
    "ratings": {
        "scent": {
            "score": "8.2",
            "votes": "33 Ratings"
        },
        "durability": {
            "score": "7.6",
            "votes": "25 Ratings"
        },
        "sillage": {
            "score": "7.5",
            "votes": "25 Ratings"
        },
        "bottle": {
            "score": "7.5",
            "votes": "32 Ratings"
        },
        "pricing": {
            "score": "9.3",
            "votes": "27 Ratings"
        }
    },
    "community_charts": {
        "Type": [
            {
                "name": "Sweet",
                "votes": 11
            },
            {
                "name": "Woody",
                "votes": 3
            },
            {
                "name": "Gourmand",
                "votes": 12
            },
            {
                "name": "Creamy",
                "votes": 9
            }
        ],
        "Style": [
            {
                "name": "Masculine",
                "votes": 8
            },
            {
                "name": "Feminine",
                "votes": 10
            },
            {
                "name": "Modern",
                "votes": 6
            }
        ],
        "Season": [
            {
                "name": "Winter",
                "votes": 12
            },
            {
                "name": "Fall",
                "votes": 11
            },
            {
                "name": "Spring",
                "votes": 3
            }
        ],
        "Occasion": [
            {
                "name": "Daily",
                "votes": 4
            },
            {
                "name": "Leisure",
                "votes": 8
            },
            {
                "name": "Night Out",
                "votes": 7
            },
            {
                "name": "Business",
                "votes": 3
            },
            {
                "name": "Evening",
                "votes": 10
            }
        ]
    }
}