{
    "name": "I Labbra e Terra",
    "brand": "Maqueda",
    "release_year": "2025",
    "description": "A new and limited perfume byMaquedafor women and men, released in2025. The scent is green-earthy. The longevity is above-average. The production was apparently discontinued.CompareLimited",
    "image_url": "https://media.parfumo.com/perfumes/25/25a706_i-labbra-e-terra-maqueda_1200.jpg?width=240&aspect_ratio=1:1",
    "main_accords": [
        "Green",
        "Earthy",
        "Floral",
        "Fruity",
        "Woody"
    ],
    "top_notes": [],
    "heart_notes": [],
    "base_notes": [],
    "ratings": {
        "scent": {
            "score": "8.3",
            "votes": "14 Ratings"
        },
        "durability": {
            "score": "8.2",
            "votes": "13 Ratings"
        },
        "sillage": {
            "score": "7.5",
            "votes": "13 Ratings"
        },
        "bottle": {
            "score": "8.1",
            "votes": "14 Ratings"
        }
    },
    "community_charts": {
        "Type": [
            {
                "name": "Spicy",
                "votes": 1
            },
            {
                "name": "Smoky",
                "votes": 2
            },
            {
                "name": "Powdery",
                "votes": 1
            },
            {
                "name": "Woody",
                "votes": 3
            },
            {
                "name": "Resinous",
                "votes": 1
            },
            {
                "name": "Green",
                "votes": 4
            },
            {
                "name": "Fruity",
                "votes": 3
            },
            {
                "name": "Earthy",
                "votes": 4
            },
            {
                "name": "Creamy",
                "votes": 1
            },
            {
                "name": "Floral",
                "votes": 3
            },
            {
                "name": "Aquatic",
                "votes": 1
            }
        ],
        "Style": [
            {
                "name": "Masculine",
                "votes": 3
            },
            {
                "name": "Feminine",
                "votes": 2
            },
            {
                "name": "Classic",
                "votes": 1
            },
            {
                "name": "Modern",
                "votes": 4
            }
        ],
        "Season": [
            {
                "name": "Winter",
                "votes": 2
            },
            {
                "name": "Fall",
                "votes": 4
            },
            {
                "name": "Summer",
                "votes": 2
            },
            {
                "name": "Spring",
                "votes": 4
            }
        ],
        "Occasion": [
            {
                "name": "Daily",
                "votes": 2
            },
            {
                "name": "Leisure",
                "votes": 4
            },
            {
                "name": "Night Out",
                "votes": 2
            },
            {
                "name": "Business",
                "votes": 1
            },
            {
                "name": "Evening",
                "votes": 4
            }
        ]
    }
}