{
    "name": "Jungle Potion",
    "brand": "Ashenfume",
    "release_year": "2025",
    "description": "A new perfume byAshenfumefor women and men, released in2025. Projection and longevity are above-average.Compare",
    "image_url": "https://media.parfumo.com/perfumes/7b/7b68f5_jungle-potion-ashenfume_1200.jpg?width=720&aspect_ratio=1:1",
    "main_accords": [],
    "top_notes": [
        "Galbanum",
        "Ginger",
        "Grapefruit",
        "Lime",
        "Skunk accord"
    ],
    "heart_notes": [
        "Blue yarrow",
        "Gardenia",
        "Tuberose"
    ],
    "base_notes": [
        "Blue cypress",
        "Gaiac wood",
        "Oakmoss",
        "White cypress"
    ],
    "ratings": {},
    "community_charts": {}
}