{
    "name": "Magico Safrano",
    "brand": "New Notes",
    "release_year": "2025",
    "description": "A new perfume byNew Notesfor women and men, released in2025. It is being marketed byHIC Beauty.Compare",
    "image_url": "https://images.parfumo.de/perfume_bottle/240.png",
    "main_accords": [],
    "top_notes": [
        "Cinnamon",
        "Nutmeg",
        "Pink pepper",
        "Saffron",
        "Tangerine"
    ],
    "heart_notes": [
        "Benzoin",
        "Labdanum",
        "Lily of the valley",
        "Tobacco"
    ],
    "base_notes": [
        "Amber",
        "Leather",
        "Mossy notes",
        "Musk",
        "Precious woods",
        "Tonka bean"
    ],
    "ratings": {},
    "community_charts": {}
}