{
    "name": "Manche",
    "brand": "Portelier",
    "release_year": "2025",
    "description": "A new perfume byPortelierfor women and men, released in2025.Compare",
    "image_url": "https://media.parfumo.com/perfumes/28/281039_manche-portelier_1200.jpg?width=720&aspect_ratio=1:1",
    "main_accords": [],
    "top_notes": [
        "Calabrian bergamot",
        "Cucumber",
        "Galbanum"
    ],
    "heart_notes": [
        "Rose",
        "Sage"
    ],
    "base_notes": [
        "Amber",
        "Kelp",
        "Sandalwood"
    ],
    "ratings": {
        "bottle": {
            "score": "6.4",
            "votes": "5 Ratings"
        }
    },
    "community_charts": {}
}