{
    "name": "Midnight Dahlia",
    "brand": "Korres",
    "release_year": "2025",
    "description": "A new perfume byKorresfor women, released in2025.Compare",
    "image_url": "https://media.parfumo.com/perfumes/be/be5bc4_midnight-dahlia-body-mist-korres_1200.jpg?width=720&aspect_ratio=1:1",
    "main_accords": [],
    "top_notes": [
        "Lychee",
        "Bergamot",
        "Dahlia"
    ],
    "heart_notes": [
        "Peony",
        "Raspberry",
        "Cedarwood"
    ],
    "base_notes": [
        "Gourmand notes",
        "Patchouli",
        "Amber"
    ],
    "ratings": {
        "bottle": {
            "score": "6.0",
            "votes": "2 Ratings"
        }
    },
    "community_charts": {}
}