{
    "name": "Platinum",
    "brand": "The Dua Brand",
    "release_year": "2025",
    "description": "A new perfume byThe Dua Brandfor women, released in2025. The perfume is vegan according to the manufacturer.PronunciationCompareVegan",
    "image_url": "https://media.parfumo.com/perfumes/57/57f41e_platinum-the-dua-brand_1200.jpg?width=720&aspect_ratio=1:1",
    "main_accords": [],
    "top_notes": [
        "Caramel",
        "Coconut",
        "Cream"
    ],
    "heart_notes": [
        "Almond milk",
        "Jasmine",
        "Mimosa"
    ],
    "base_notes": [
        "Vanilla",
        "White musk"
    ],
    "ratings": {},
    "community_charts": {}
}