{
    "name": "Pure OUDDiction",
    "brand": "The Gate",
    "release_year": "2025",
    "description": "A new perfume byThe Gatefor women and men, released in2025.Compare",
    "image_url": "https://media.parfumo.com/perfumes/9c/9c0ec9_pure-ouddiction-extrait-de-parfum-the-gate_1200.jpg?width=720&aspect_ratio=1:1",
    "main_accords": [],
    "top_notes": [
        "Cannabis",
        "Maté",
        "Cardamom",
        "Sage"
    ],
    "heart_notes": [
        "Glycyrrhiza glabra",
        "Hay",
        "Fir balsam",
        "Suede"
    ],
    "base_notes": [
        "Smoky notes",
        "Vetiver",
        "Musk",
        "Oud",
        "Patchouli"
    ],
    "ratings": {
        "scent": {
            "score": "7.8",
            "votes": "2 Ratings"
        },
        "durability": {
            "score": "7.5",
            "votes": "2 Ratings"
        },
        "sillage": {
            "score": "7.5",
            "votes": "2 Ratings"
        },
        "bottle": {
            "score": "6.8",
            "votes": "4 Ratings"
        }
    },
    "community_charts": {}
}