{
    "name": "Raag Neela",
    "brand": "Jogi",
    "release_year": "2025",
    "description": "A new perfume byJogifor women and men, released in2025. The scent is floral-creamy. Projection and longevity are above-average.Compare",
    "image_url": "https://media.parfumo.com/perfumes/08/08b098_raag-neela-jogi_1200.jpg?width=720&aspect_ratio=1:1",
    "main_accords": [
        "Floral",
        "Creamy",
        "Woody",
        "Resinous",
        "Animal"
    ],
    "top_notes": [],
    "heart_notes": [],
    "base_notes": [],
    "ratings": {
        "scent": {
            "score": "9.5",
            "votes": "6 Ratings"
        },
        "durability": {
            "score": "9.0",
            "votes": "6 Ratings"
        },
        "sillage": {
            "score": "8.8",
            "votes": "6 Ratings"
        },
        "bottle": {
            "score": "8.7",
            "votes": "7 Ratings"
        }
    },
    "community_charts": {
        "Type": [
            {
                "name": "Spicy",
                "votes": 1
            },
            {
                "name": "Sweet",
                "votes": 1
            },
            {
                "name": "Powdery",
                "votes": 1
            },
            {
                "name": "Oriental",
                "votes": 1
            },
            {
                "name": "Woody",
                "votes": 2
            },
            {
                "name": "Resinous",
                "votes": 2
            },
            {
                "name": "Green",
                "votes": 1
            },
            {
                "name": "Fresh",
                "votes": 1
            },
            {
                "name": "Earthy",
                "votes": 1
            },
            {
                "name": "Creamy",
                "votes": 3
            },
            {
                "name": "Floral",
                "votes": 4
            },
            {
                "name": "Aquatic",
                "votes": 1
            },
            {
                "name": "Animal",
                "votes": 2
            }
        ],
        "Style": [
            {
                "name": "Masculine",
                "votes": 4
            },
            {
                "name": "Feminine",
                "votes": 4
            },
            {
                "name": "Classic",
                "votes": 3
            }
        ],
        "Season": [
            {
                "name": "Winter",
                "votes": 3
            },
            {
                "name": "Fall",
                "votes": 4
            },
            {
                "name": "Summer",
                "votes": 3
            },
            {
                "name": "Spring",
                "votes": 4
            }
        ],
        "Occasion": [
            {
                "name": "Daily",
                "votes": 2
            },
            {
                "name": "Leisure",
                "votes": 3
            },
            {
                "name": "Night Out",
                "votes": 1
            },
            {
                "name": "Business",
                "votes": 2
            },
            {
                "name": "Evening",
                "votes": 1
            }
        ]
    }
}