{
    "name": "Roasted Tangerine",
    "brand": "Liquides Imaginaires",
    "release_year": "2025",
    "description": "A new perfume byLiquides Imaginairesfor women and men, released in2025. The scent is citrusy-spicy.PronunciationCompare",
    "image_url": "https://media.parfumo.com/perfumes/e5/e57d87_roasted-tangerine-liquides-imaginaires_1200.jpg?width=480&aspect_ratio=1:1",
    "main_accords": [
        "Citrus",
        "Spicy",
        "Woody",
        "Fruity",
        "Fresh"
    ],
    "top_notes": [
        "Blood orange",
        "Italian bergamot Orpur®",
        "Italian mandarine Orpur®"
    ],
    "heart_notes": [
        "Coffee absolute",
        "Frankincense",
        "Ginger Orpur®",
        "Petitgrain Orpur®",
        "Roasted fennel seed"
    ],
    "base_notes": [
        "Ambrofix",
        "Atlas cedar Orpur®",
        "Oud",
        "Smoked wood",
        "Tonka bean absolute Orpur®",
        "White musk"
    ],
    "ratings": {
        "scent": {
            "score": "7.4",
            "votes": "6 Ratings"
        },
        "durability": {
            "score": "7.0",
            "votes": "2 Ratings"
        },
        "sillage": {
            "score": "6.3",
            "votes": "3 Ratings"
        },
        "bottle": {
            "score": "6.7",
            "votes": "6 Ratings"
        }
    },
    "community_charts": {}
}