{
    "name": "Saffron+Sugar",
    "brand": "Michael Malul",
    "release_year": "2025",
    "description": "A new perfume byMichael Malulfor women, released in2025.Compare",
    "image_url": "https://media.parfumo.com/perfumes/b4/b4fcf5_saffron-sugar-michael-malul_1200.jpg?width=720&aspect_ratio=1:1",
    "main_accords": [],
    "top_notes": [
        "Bergamot",
        "Lemon zest",
        "Pear",
        "Pink pepper"
    ],
    "heart_notes": [
        "Jasmine",
        "Raspberry",
        "Red rose",
        "Saffron"
    ],
    "base_notes": [
        "Amber",
        "Caramel",
        "Musk",
        "Oakmoss",
        "Patchouli",
        "Sandalwood"
    ],
    "ratings": {},
    "community_charts": {}
}