{
    "name": "Single Era",
    "brand": "Claire's",
    "release_year": "2025",
    "description": "A new perfume byClaire'sfor women, released in2025. It is being marketed byCBI Distributing Corp..Compare",
    "image_url": "https://media.parfumo.com/perfumes/91/91b817_single-era-claire-s_1200.jpg?width=720&aspect_ratio=1:1",
    "main_accords": [],
    "top_notes": [
        "Passion fruit",
        "Raspberry",
        "Sichuan pepper"
    ],
    "heart_notes": [
        "Blossoms",
        "Musk",
        "Orange blossom",
        "Peony"
    ],
    "base_notes": [
        "Ambroxan",
        "Oak wood",
        "Pink musk"
    ],
    "ratings": {},
    "community_charts": {}
}