{
    "name": "Siren Spell",
    "brand": "Deck of Scarlet",
    "release_year": "2025",
    "description": "A new perfume byDeck of Scarletfor women, released in2025. The scent is fresh-woody. The perfume is vegan according to the manufacturer.PronunciationCompareVegan",
    "image_url": "https://media.parfumo.com/perfumes/20/20e2f1_siren-spell-deck-of-scarlet_1200.jpg?width=720&aspect_ratio=1:1",
    "main_accords": [
        "Fresh",
        "Woody",
        "Powdery",
        "Creamy"
    ],
    "top_notes": [
        "Bergamot"
    ],
    "heart_notes": [
        "Jasmine",
        "Neroli"
    ],
    "base_notes": [
        "Cedar",
        "Sensual skin accord"
    ],
    "ratings": {},
    "community_charts": {
        "Type": [
            {
                "name": "Powdery",
                "votes": 1
            },
            {
                "name": "Woody",
                "votes": 1
            },
            {
                "name": "Fresh",
                "votes": 1
            },
            {
                "name": "Creamy",
                "votes": 1
            }
        ],
        "Style": [
            {
                "name": "Feminine",
                "votes": 1
            },
            {
                "name": "Classic",
                "votes": 1
            }
        ],
        "Season": [
            {
                "name": "Winter",
                "votes": 1
            },
            {
                "name": "Fall",
                "votes": 1
            },
            {
                "name": "Spring",
                "votes": 1
            }
        ],
        "Occasion": [
            {
                "name": "Daily",
                "votes": 1
            },
            {
                "name": "Leisure",
                "votes": 1
            },
            {
                "name": "Night Out",
                "votes": 1
            },
            {
                "name": "Evening",
                "votes": 1
            }
        ]
    }
}