{
    "name": "Suez Oud",
    "brand": "Monreale",
    "release_year": "2025",
    "description": "A new and limited perfume byMonrealefor women and men, released in2025.CompareLimited",
    "image_url": "https://media.parfumo.com/perfumes/7a/7a60c9_suez-oud-monreale_1200.jpg?width=720&aspect_ratio=1:1",
    "main_accords": [],
    "top_notes": [],
    "heart_notes": [],
    "base_notes": [],
    "ratings": {
        "bottle": {
            "score": "7.0",
            "votes": "2 Ratings"
        }
    },
    "community_charts": {}
}