{
    "name": "Valer",
    "brand": "Armaf",
    "release_year": "2025",
    "description": "A new perfume byArmaffor women and men, released in2025. It is being marketed bySterling Perfumes Industries LLC.Compare",
    "image_url": "https://media.parfumo.com/perfumes/cc/cc4cb8_valer-armaf_1200.jpg?width=720&aspect_ratio=1:1",
    "main_accords": [],
    "top_notes": [
        "Bergamot",
        "Grapefruit",
        "Mandarin orange",
        "Mint"
    ],
    "heart_notes": [
        "Frankincense",
        "Geranium",
        "Lavender",
        "Rosemary"
    ],
    "base_notes": [
        "Amber",
        "Cashmeran",
        "Cedar",
        "Patchouli",
        "Sandalwood",
        "Vetiver"
    ],
    "ratings": {},
    "community_charts": {}
}