{
    "name": "Vanilla Love",
    "brand": "RudRoss",
    "release_year": "2025",
    "description": "A new perfume byRudRossfor women and men, released in2025. The scent is fruity-aquatic.Compare",
    "image_url": "https://media.parfumo.com/perfumes/63/6385f0_vanilla-love-rudross_1200.jpg?width=480&aspect_ratio=1:1",
    "main_accords": [
        "Fruity",
        "Aquatic",
        "Gourmand"
    ],
    "top_notes": [
        "Bergamot",
        "Chocolate",
        "Vanilla"
    ],
    "heart_notes": [
        "Chamomile",
        "Hedione",
        "White blossoms"
    ],
    "base_notes": [
        "Musk",
        "Sandalwood",
        "Tonka bean"
    ],
    "ratings": {},
    "community_charts": {}
}