{
    "name": "Zodiac Solmaris",
    "brand": "Paris Corner",
    "release_year": "2025",
    "description": "A new perfume byParis Cornerfor women and men, released in2025. The scent is aquatic-fresh. It is being marketed byParis Corner Perfumes.Compare",
    "image_url": "https://media.parfumo.com/perfumes/ae/aeb9c1_zodiac-solmaris-paris-corner_1200.jpg?width=720&aspect_ratio=1:1",
    "main_accords": [
        "Aquatic",
        "Fresh",
        "Synthetic",
        "Sweet",
        "Citrus"
    ],
    "top_notes": [
        "Ginger",
        "Sea salt"
    ],
    "heart_notes": [
        "Algae",
        "Aquatic notes"
    ],
    "base_notes": [
        "Cedarwood",
        "Oakmoss",
        "Vetiver"
    ],
    "ratings": {
        "scent": {
            "score": "6.8",
            "votes": "2 Ratings"
        },
        "durability": {
            "score": "6.5",
            "votes": "2 Ratings"
        },
        "sillage": {
            "score": "7.5",
            "votes": "2 Ratings"
        },
        "bottle": {
            "score": "7.0",
            "votes": "3 Ratings"
        }
    },
    "community_charts": {
        "Type": [
            {
                "name": "Citrus",
                "votes": 1
            },
            {
                "name": "Spicy",
                "votes": 1
            },
            {
                "name": "Synthetic",
                "votes": 1
            },
            {
                "name": "Sweet",
                "votes": 1
            },
            {
                "name": "Oriental",
                "votes": 1
            },
            {
                "name": "Fresh",
                "votes": 2
            },
            {
                "name": "Creamy",
                "votes": 1
            },
            {
                "name": "Floral",
                "votes": 1
            },
            {
                "name": "Aquatic",
                "votes": 2
            }
        ],
        "Style": [
            {
                "name": "Masculine",
                "votes": 1
            },
            {
                "name": "Classic",
                "votes": 1
            },
            {
                "name": "Modern",
                "votes": 2
            }
        ],
        "Season": [
            {
                "name": "Fall",
                "votes": 1
            },
            {
                "name": "Summer",
                "votes": 2
            },
            {
                "name": "Spring",
                "votes": 2
            }
        ],
        "Occasion": [
            {
                "name": "Daily",
                "votes": 2
            },
            {
                "name": "Sport",
                "votes": 2
            },
            {
                "name": "Leisure",
                "votes": 2
            },
            {
                "name": "Night Out",
                "votes": 1
            },
            {
                "name": "Business",
                "votes": 1
            },
            {
                "name": "Evening",
                "votes": 1
            }
        ]
    }
}